odoo/addons/contract_group_somconnexio/CHANGELOG.md
odoo/addons/contract_group_somconnexio/README.rst
odoo/addons/contract_group_somconnexio/__init__.py
odoo/addons/contract_group_somconnexio/__manifest__.py
odoo/addons/contract_group_somconnexio/data/contract_group.xml
odoo/addons/contract_group_somconnexio/demo/contract_group.xml
odoo/addons/contract_group_somconnexio/models/__init__.py
odoo/addons/contract_group_somconnexio/models/change_partner_emails.py
odoo/addons/contract_group_somconnexio/models/contract.py
odoo/addons/contract_group_somconnexio/models/contract_group.py
odoo/addons/contract_group_somconnexio/models/res_partner.py
odoo/addons/contract_group_somconnexio/security/ir.model.access.csv
odoo/addons/contract_group_somconnexio/tests/__init__.py
odoo/addons/contract_group_somconnexio/tests/models/__init__.py
odoo/addons/contract_group_somconnexio/tests/models/test_contract.py
odoo/addons/contract_group_somconnexio/tests/models/test_contract_group.py
odoo/addons/contract_group_somconnexio/tests/wizards/__init__.py
odoo/addons/contract_group_somconnexio/tests/wizards/test_contract_group_change_wizard.py
odoo/addons/contract_group_somconnexio/views/account_move.xml
odoo/addons/contract_group_somconnexio/views/contract.xml
odoo/addons/contract_group_somconnexio/wizards/__init__.py
odoo/addons/contract_group_somconnexio/wizards/contract_email_change.py/__init__.py
odoo/addons/contract_group_somconnexio/wizards/contract_email_change.py/contract_iban_change.py
odoo/addons/contract_group_somconnexio/wizards/contract_email_change.py/contract_iban_change.xml
odoo/addons/contract_group_somconnexio/wizards/contract_group_change/__init__.py
odoo/addons/contract_group_somconnexio/wizards/contract_group_change/contract_group_change.py
odoo/addons/contract_group_somconnexio/wizards/contract_group_change/contract_group_change.xml
odoo/addons/contract_group_somconnexio/wizards/contract_iban_change/__init__.py
odoo_addon_contract_group_somconnexio-16.0.1.0.3.dist-info/METADATA
odoo_addon_contract_group_somconnexio-16.0.1.0.3.dist-info/WHEEL
odoo_addon_contract_group_somconnexio-16.0.1.0.3.dist-info/top_level.txt
odoo_addon_contract_group_somconnexio-16.0.1.0.3.dist-info/RECORD
